nbtimebar/__init__.py
nbtimebar/main.py
nbtimebar-0.2.1.dist-info/LICENSE
nbtimebar-0.2.1.dist-info/METADATA
nbtimebar-0.2.1.dist-info/WHEEL
nbtimebar-0.2.1.dist-info/top_level.txt
nbtimebar-0.2.1.dist-info/RECORD
